{"D:\\Github\\Japalura\\AppScope\\app.json5":{"hashValue":"8eb2ec0faf2820aa662bfdd2265fcaaa","name":"app.json5","path":"D:\\Github\\Japalura\\AppScope\\app.json5","type":"file","isSymbolicLink":false,"fileMetaData":{"size":223,"lastModifiedTime":1698032792000}},"D:\\Github\\Japalura\\entry\\src\\main\\module.json5":{"hashValue":"8d74e5d8068317ceeebe602c19a8a2e3","name":"module.json5","path":"D:\\Github\\Japalura\\entry\\src\\main\\module.json5","type":"file","isSymbolicLink":false,"fileMetaData":{"size":1805,"lastModifiedTime":1698032792000}},"D:\\Github\\Japalura\\entry\\build\\default\\intermediates\\hap_metadata\\default\\output_metadata.json":{"hashValue":"d00682b7aca19998c54995c6e1aa9cf6","name":"output_metadata.json","path":"D:\\Github\\Japalura\\entry\\build\\default\\intermediates\\hap_metadata\\default\\output_metadata.json","type":"file","isSymbolicLink":false,"fileMetaData":{"size":86,"lastModifiedTime":1701744444923}},"D:\\Github\\Japalura\\entry\\build\\default\\intermediates\\merge_profile\\default\\module.json":{"hashValue":"8809a3b4002a89da7bd27a30f091a8a1","name":"module.json","path":"D:\\Github\\Japalura\\entry\\build\\default\\intermediates\\merge_profile\\default\\module.json","type":"file","isSymbolicLink":false,"fileMetaData":{"size":1747,"lastModifiedTime":1701744444935}},"D:\\Github\\Japalura\\entry\\build\\default\\intermediates\\loader\\default\\loader.json":{"hashValue":"d764508f7fbf174db6fc1191cf1d058d","name":"loader.json","path":"D:\\Github\\Japalura\\entry\\build\\default\\intermediates\\loader\\default\\loader.json","type":"file","isSymbolicLink":false,"fileMetaData":{"size":478,"lastModifiedTime":1701744444949}},"D:\\Github\\Japalura\\entry\\build\\default\\outputs\\default\\pack.info":{"hashValue":"57bf1dea7ae67326befe82abeda199c0","name":"pack.info","path":"D:\\Github\\Japalura\\entry\\build\\default\\outputs\\default\\pack.info","type":"file","isSymbolicLink":false,"fileMetaData":{"size":532,"lastModifiedTime":1701744444959}},"D:\\Github\\Japalura\\entry\\build\\default\\intermediates\\process_profile\\default\\module.json":{"hashValue":"1b6c1a26b21e1ff4462a0b28455fd5a0","name":"module.json","path":"D:\\Github\\Japalura\\entry\\build\\default\\intermediates\\process_profile\\default\\module.json","type":"file","isSymbolicLink":false,"fileMetaData":{"size":1832,"lastModifiedTime":1701744445262}},"D:\\Github\\Japalura\\entry\\build\\default\\intermediates\\res\\default\\resConfig.json":{"hashValue":"2230d7f6ef4e36b2fa0aaee1d3cd00ea","name":"resConfig.json","path":"D:\\Github\\Japalura\\entry\\build\\default\\intermediates\\res\\default\\resConfig.json","type":"file","isSymbolicLink":false,"fileMetaData":{"size":526,"lastModifiedTime":1701744445272}},"D:\\Github\\Japalura\\entry\\build\\default\\intermediates\\libs\\default":{"hashValue":"","name":"default","path":"D:\\Github\\Japalura\\entry\\build\\default\\intermediates\\libs\\default","type":"directory","isSymbolicLink":false,"children":[]},"D:\\Github\\Japalura\\entry\\src\\main\\resources":{"hashValue":"1ed2a42ba7cdaee0edb5d647a43e4b7a","name":"resources","path":"D:\\Github\\Japalura\\entry\\src\\main\\resources","type":"directory","isSymbolicLink":false,"children":[{"hashValue":"7023f2fb7a863cf41028184193b76937","name":"base","path":"D:\\Github\\Japalura\\entry\\src\\main\\resources\\base","type":"directory","isSymbolicLink":false,"children":[{"hashValue":"29c2e0f1d6b7db669ac4e194ee7bf1e0","name":"element","path":"D:\\Github\\Japalura\\entry\\src\\main\\resources\\base\\element","type":"directory","isSymbolicLink":false,"children":[{"hashValue":"cacdc6c5439ffc8d90ee199d0dc5078a","name":"color.json","path":"D:\\Github\\Japalura\\entry\\src\\main\\resources\\base\\element\\color.json","type":"file","isSymbolicLink":false,"fileMetaData":{"size":105,"lastModifiedTime":1698032792000}},{"hashValue":"3ab927d9aeb7016a6cb9adbe7f9cf659","name":"float.json","path":"D:\\Github\\Japalura\\entry\\src\\main\\resources\\base\\element\\float.json","type":"file","isSymbolicLink":false,"fileMetaData":{"size":1427,"lastModifiedTime":1698032792000}},{"hashValue":"512c31542b20d7ef48c7de1b397eee18","name":"string.json","path":"D:\\Github\\Japalura\\entry\\src\\main\\resources\\base\\element\\string.json","type":"file","isSymbolicLink":false,"fileMetaData":{"size":1190,"lastModifiedTime":1698032792000}}]},{"hashValue":"2393604763be487d45a7ff9e9127fa1b","name":"media","path":"D:\\Github\\Japalura\\entry\\src\\main\\resources\\base\\media","type":"directory","isSymbolicLink":false,"children":[{"hashValue":"88086604bdd89994d4e56e2231ce70d4","name":"ic_adjust_filled.png","path":"D:\\Github\\Japalura\\entry\\src\\main\\resources\\base\\media\\ic_adjust_filled.png","type":"file","isSymbolicLink":false,"fileMetaData":{"size":2682,"lastModifiedTime":1698032792000}},{"hashValue":"2902d4d7ed783be0dcb036118340c672","name":"ic_adjust.png","path":"D:\\Github\\Japalura\\entry\\src\\main\\resources\\base\\media\\ic_adjust.png","type":"file","isSymbolicLink":false,"fileMetaData":{"size":1876,"lastModifiedTime":1698032792000}},{"hashValue":"c7459d16d3e71b34392050b605fff731","name":"ic_anti_clockwise.png","path":"D:\\Github\\Japalura\\entry\\src\\main\\resources\\base\\media\\ic_anti_clockwise.png","type":"file","isSymbolicLink":false,"fileMetaData":{"size":1788,"lastModifiedTime":1698032792000}},{"hashValue":"ae6f78e69f8c64a0d14cf65c46717acf","name":"ic_brightness_filled.png","path":"D:\\Github\\Japalura\\entry\\src\\main\\resources\\base\\media\\ic_brightness_filled.png","type":"file","isSymbolicLink":false,"fileMetaData":{"size":3875,"lastModifiedTime":1698032792000}},{"hashValue":"b2bbf1e56363f96531af260603770218","name":"ic_brightness.png","path":"D:\\Github\\Japalura\\entry\\src\\main\\resources\\base\\media\\ic_brightness.png","type":"file","isSymbolicLink":false,"fileMetaData":{"size":2607,"lastModifiedTime":1698032792000}},{"hashValue":"568780f5edf38dcecd548e828addfa34","name":"ic_clockwise.png","path":"D:\\Github\\Japalura\\entry\\src\\main\\resources\\base\\media\\ic_clockwise.png","type":"file","isSymbolicLink":false,"fileMetaData":{"size":1881,"lastModifiedTime":1698032792000}},{"hashValue":"8e5dc91eca088e0041a9ba9b85111341","name":"ic_crop_filled.png","path":"D:\\Github\\Japalura\\entry\\src\\main\\resources\\base\\media\\ic_crop_filled.png","type":"file","isSymbolicLink":false,"fileMetaData":{"size":1592,"lastModifiedTime":1698032792000}},{"hashValue":"c50eb56c591fd528aa56e3678f027629","name":"ic_crop.png","path":"D:\\Github\\Japalura\\entry\\src\\main\\resources\\base\\media\\ic_crop.png","type":"file","isSymbolicLink":false,"fileMetaData":{"size":1221,"lastModifiedTime":1698032792000}},{"hashValue":"7130d2237bdb6473016b0405d6155fb1","name":"ic_four2three_filled.png","path":"D:\\Github\\Japalura\\entry\\src\\main\\resources\\base\\media\\ic_four2three_filled.png","type":"file","isSymbolicLink":false,"fileMetaData":{"size":2073,"lastModifiedTime":1698032792000}},{"hashValue":"7b9300e26ee9c91ce3d5bfea1d3456a1","name":"ic_four2three.png","path":"D:\\Github\\Japalura\\entry\\src\\main\\resources\\base\\media\\ic_four2three.png","type":"file","isSymbolicLink":false,"fileMetaData":{"size":1764,"lastModifiedTime":1698032792000}},{"hashValue":"0dfdf79443d0a828f9dde70c302b3788","name":"ic_low.jpg","path":"D:\\Github\\Japalura\\entry\\src\\main\\resources\\base\\media\\ic_low.jpg","type":"file","isSymbolicLink":false,"fileMetaData":{"size":1720314,"lastModifiedTime":1698032792000}},{"hashValue":"77a72ec989083c315fd01a2c1db20215","name":"ic_one2one_filled.png","path":"D:\\Github\\Japalura\\entry\\src\\main\\resources\\base\\media\\ic_one2one_filled.png","type":"file","isSymbolicLink":false,"fileMetaData":{"size":1318,"lastModifiedTime":1698032792000}},{"hashValue":"41f86e36de645306aef3dca6f2709798","name":"ic_one2one.png","path":"D:\\Github\\Japalura\\entry\\src\\main\\resources\\base\\media\\ic_one2one.png","type":"file","isSymbolicLink":false,"fileMetaData":{"size":1190,"lastModifiedTime":1698032792000}},{"hashValue":"09101b4f320abae10b6b02d92ea7138b","name":"ic_original_filled.png","path":"D:\\Github\\Japalura\\entry\\src\\main\\resources\\base\\media\\ic_original_filled.png","type":"file","isSymbolicLink":false,"fileMetaData":{"size":875,"lastModifiedTime":1698032792000}},{"hashValue":"dfa3c79f3e9e90d3d70f3a04797ad81e","name":"ic_original.png","path":"D:\\Github\\Japalura\\entry\\src\\main\\resources\\base\\media\\ic_original.png","type":"file","isSymbolicLink":false,"fileMetaData":{"size":906,"lastModifiedTime":1698032792000}},{"hashValue":"6350546ea13cb77c8ce42ed1a73a57f4","name":"ic_reset.png","path":"D:\\Github\\Japalura\\entry\\src\\main\\resources\\base\\media\\ic_reset.png","type":"file","isSymbolicLink":false,"fileMetaData":{"size":2975,"lastModifiedTime":1698032792000}},{"hashValue":"4e56ee16ca6306cb4897c1019a8f8cac","name":"ic_rotate_filled.png","path":"D:\\Github\\Japalura\\entry\\src\\main\\resources\\base\\media\\ic_rotate_filled.png","type":"file","isSymbolicLink":false,"fileMetaData":{"size":2981,"lastModifiedTime":1698032792000}},{"hashValue":"d6785fa4621e2b162e8eb064d5df0cc0","name":"ic_rotate.png","path":"D:\\Github\\Japalura\\entry\\src\\main\\resources\\base\\media\\ic_rotate.png","type":"file","isSymbolicLink":false,"fileMetaData":{"size":2288,"lastModifiedTime":1698032792000}},{"hashValue":"685e937c8c01997fcfa564a91d0148c8","name":"ic_saturation_filled.png","path":"D:\\Github\\Japalura\\entry\\src\\main\\resources\\base\\media\\ic_saturation_filled.png","type":"file","isSymbolicLink":false,"fileMetaData":{"size":3810,"lastModifiedTime":1698032792000}},{"hashValue":"fd0d132daf72b0dd060359fff99c9a3b","name":"ic_saturation.png","path":"D:\\Github\\Japalura\\entry\\src\\main\\resources\\base\\media\\ic_saturation.png","type":"file","isSymbolicLink":false,"fileMetaData":{"size":3733,"lastModifiedTime":1698032792000}},{"hashValue":"682afb4da6c5329e902464493f8f6ded","name":"ic_save.png","path":"D:\\Github\\Japalura\\entry\\src\\main\\resources\\base\\media\\ic_save.png","type":"file","isSymbolicLink":false,"fileMetaData":{"size":2003,"lastModifiedTime":1698032792000}},{"hashValue":"25b07d602ae75ee387323bd996217d70","name":"ic_sixteen2nine_filled.png","path":"D:\\Github\\Japalura\\entry\\src\\main\\resources\\base\\media\\ic_sixteen2nine_filled.png","type":"file","isSymbolicLink":false,"fileMetaData":{"size":2159,"lastModifiedTime":1698032792000}},{"hashValue":"b30f2e0deb13caa1711bc5294dfb6fd6","name":"ic_sixteen2nine.png","path":"D:\\Github\\Japalura\\entry\\src\\main\\resources\\base\\media\\ic_sixteen2nine.png","type":"file","isSymbolicLink":false,"fileMetaData":{"size":1787,"lastModifiedTime":1698032792000}},{"hashValue":"3a85a13c968828bbb0080a56132dcda4","name":"ic_transparency_filled.png","path":"D:\\Github\\Japalura\\entry\\src\\main\\resources\\base\\media\\ic_transparency_filled.png","type":"file","isSymbolicLink":false,"fileMetaData":{"size":3440,"lastModifiedTime":1698032792000}},{"hashValue":"1c635c13f34c84ad644dd07a81a3c90b","name":"ic_transparency.png","path":"D:\\Github\\Japalura\\entry\\src\\main\\resources\\base\\media\\ic_transparency.png","type":"file","isSymbolicLink":false,"fileMetaData":{"size":2638,"lastModifiedTime":1698032792000}},{"hashValue":"e0ca921d52e101d5d9a64795071c9840","name":"icon.png","path":"D:\\Github\\Japalura\\entry\\src\\main\\resources\\base\\media\\icon.png","type":"file","isSymbolicLink":false,"fileMetaData":{"size":6790,"lastModifiedTime":1698032792000}}]},{"hashValue":"dfa0b78ac08b964d4fccce2bcc077ab5","name":"profile","path":"D:\\Github\\Japalura\\entry\\src\\main\\resources\\base\\profile","type":"directory","isSymbolicLink":false,"children":[{"hashValue":"4bbf78799f8a2dbf7bfbec0331266386","name":"main_pages.json","path":"D:\\Github\\Japalura\\entry\\src\\main\\resources\\base\\profile\\main_pages.json","type":"file","isSymbolicLink":false,"fileMetaData":{"size":43,"lastModifiedTime":1698032792000}}]}]},{"hashValue":"73ca77737b2964eb048df5684264fdfb","name":"en_US","path":"D:\\Github\\Japalura\\entry\\src\\main\\resources\\en_US","type":"directory","isSymbolicLink":false,"children":[{"hashValue":"86dbb4fa74ec306573d8d4f1a3808518","name":"element","path":"D:\\Github\\Japalura\\entry\\src\\main\\resources\\en_US\\element","type":"directory","isSymbolicLink":false,"children":[{"hashValue":"512c31542b20d7ef48c7de1b397eee18","name":"string.json","path":"D:\\Github\\Japalura\\entry\\src\\main\\resources\\en_US\\element\\string.json","type":"file","isSymbolicLink":false,"fileMetaData":{"size":1190,"lastModifiedTime":1698032792000}}]}]},{"hashValue":"ee65c96a71abd477c92e8373f19d61f3","name":"rawfile","path":"D:\\Github\\Japalura\\entry\\src\\main\\resources\\rawfile","type":"directory","isSymbolicLink":false,"children":[{"hashValue":"c712f35b6643285bb54dcc23064a4aa5","name":"low.jpg","path":"D:\\Github\\Japalura\\entry\\src\\main\\resources\\rawfile\\low.jpg","type":"file","isSymbolicLink":false,"fileMetaData":{"size":1720314,"lastModifiedTime":1698032792000}}]}]},"D:\\Github\\Japalura\\AppScope\\resources":{"hashValue":"688c6fbdee64f3696534fb6a84809f7b","name":"resources","path":"D:\\Github\\Japalura\\AppScope\\resources","type":"directory","isSymbolicLink":false,"children":[{"hashValue":"9e82209fe085076578810da4e34638bf","name":"base","path":"D:\\Github\\Japalura\\AppScope\\resources\\base","type":"directory","isSymbolicLink":false,"children":[{"hashValue":"c886e5b73053c6edef16e43f8a004bf0","name":"element","path":"D:\\Github\\Japalura\\AppScope\\resources\\base\\element","type":"directory","isSymbolicLink":false,"children":[{"hashValue":"b28b363e5e7741598f29af29356752fe","name":"string.json","path":"D:\\Github\\Japalura\\AppScope\\resources\\base\\element\\string.json","type":"file","isSymbolicLink":false,"fileMetaData":{"size":94,"lastModifiedTime":1701744632927}}]},{"hashValue":"b97addf066da17bda2ac736dbdee1688","name":"media","path":"D:\\Github\\Japalura\\AppScope\\resources\\base\\media","type":"directory","isSymbolicLink":false,"children":[{"hashValue":"24d7fb7a55a72b5304fe119a3b8daa6f","name":"app_icon.png","path":"D:\\Github\\Japalura\\AppScope\\resources\\base\\media\\app_icon.png","type":"file","isSymbolicLink":false,"fileMetaData":{"size":6790,"lastModifiedTime":1698032792000}}]}]}]},"D:\\Github\\Japalura\\entry\\build\\default\\intermediates\\res\\default":{"hashValue":"89ec0a91ed9012dad625e769e73b373e","name":"default","path":"D:\\Github\\Japalura\\entry\\build\\default\\intermediates\\res\\default","type":"directory","isSymbolicLink":false,"children":[{"hashValue":"607a436c09420a260bf12fba1ea83946","name":"module.json","path":"D:\\Github\\Japalura\\entry\\build\\default\\intermediates\\res\\default\\module.json","type":"file","isSymbolicLink":false,"fileMetaData":{"size":3458,"lastModifiedTime":1701744980021}},{"hashValue":"2230d7f6ef4e36b2fa0aaee1d3cd00ea","name":"resConfig.json","path":"D:\\Github\\Japalura\\entry\\build\\default\\intermediates\\res\\default\\resConfig.json","type":"file","isSymbolicLink":false,"fileMetaData":{"size":526,"lastModifiedTime":1701744445272}},{"hashValue":"9fcd16d3a213e2b3072f3e3450e7209e","name":"resources","path":"D:\\Github\\Japalura\\entry\\build\\default\\intermediates\\res\\default\\resources","type":"directory","isSymbolicLink":false,"children":[{"hashValue":"627ae185d7c80a27bc9e6593d01b2c93","name":"base","path":"D:\\Github\\Japalura\\entry\\build\\default\\intermediates\\res\\default\\resources\\base","type":"directory","isSymbolicLink":false,"children":[{"hashValue":"541d81193ed96814b245f998cff73fee","name":"media","path":"D:\\Github\\Japalura\\entry\\build\\default\\intermediates\\res\\default\\resources\\base\\media","type":"directory","isSymbolicLink":false,"children":[{"hashValue":"24d7fb7a55a72b5304fe119a3b8daa6f","name":"app_icon.png","path":"D:\\Github\\Japalura\\entry\\build\\default\\intermediates\\res\\default\\resources\\base\\media\\app_icon.png","type":"file","isSymbolicLink":false,"fileMetaData":{"size":6790,"lastModifiedTime":1698032792000}},{"hashValue":"88086604bdd89994d4e56e2231ce70d4","name":"ic_adjust_filled.png","path":"D:\\Github\\Japalura\\entry\\build\\default\\intermediates\\res\\default\\resources\\base\\media\\ic_adjust_filled.png","type":"file","isSymbolicLink":false,"fileMetaData":{"size":2682,"lastModifiedTime":1698032792000}},{"hashValue":"2902d4d7ed783be0dcb036118340c672","name":"ic_adjust.png","path":"D:\\Github\\Japalura\\entry\\build\\default\\intermediates\\res\\default\\resources\\base\\media\\ic_adjust.png","type":"file","isSymbolicLink":false,"fileMetaData":{"size":1876,"lastModifiedTime":1698032792000}},{"hashValue":"c7459d16d3e71b34392050b605fff731","name":"ic_anti_clockwise.png","path":"D:\\Github\\Japalura\\entry\\build\\default\\intermediates\\res\\default\\resources\\base\\media\\ic_anti_clockwise.png","type":"file","isSymbolicLink":false,"fileMetaData":{"size":1788,"lastModifiedTime":1698032792000}},{"hashValue":"ae6f78e69f8c64a0d14cf65c46717acf","name":"ic_brightness_filled.png","path":"D:\\Github\\Japalura\\entry\\build\\default\\intermediates\\res\\default\\resources\\base\\media\\ic_brightness_filled.png","type":"file","isSymbolicLink":false,"fileMetaData":{"size":3875,"lastModifiedTime":1698032792000}},{"hashValue":"b2bbf1e56363f96531af260603770218","name":"ic_brightness.png","path":"D:\\Github\\Japalura\\entry\\build\\default\\intermediates\\res\\default\\resources\\base\\media\\ic_brightness.png","type":"file","isSymbolicLink":false,"fileMetaData":{"size":2607,"lastModifiedTime":1698032792000}},{"hashValue":"568780f5edf38dcecd548e828addfa34","name":"ic_clockwise.png","path":"D:\\Github\\Japalura\\entry\\build\\default\\intermediates\\res\\default\\resources\\base\\media\\ic_clockwise.png","type":"file","isSymbolicLink":false,"fileMetaData":{"size":1881,"lastModifiedTime":1698032792000}},{"hashValue":"8e5dc91eca088e0041a9ba9b85111341","name":"ic_crop_filled.png","path":"D:\\Github\\Japalura\\entry\\build\\default\\intermediates\\res\\default\\resources\\base\\media\\ic_crop_filled.png","type":"file","isSymbolicLink":false,"fileMetaData":{"size":1592,"lastModifiedTime":1698032792000}},{"hashValue":"c50eb56c591fd528aa56e3678f027629","name":"ic_crop.png","path":"D:\\Github\\Japalura\\entry\\build\\default\\intermediates\\res\\default\\resources\\base\\media\\ic_crop.png","type":"file","isSymbolicLink":false,"fileMetaData":{"size":1221,"lastModifiedTime":1698032792000}},{"hashValue":"7130d2237bdb6473016b0405d6155fb1","name":"ic_four2three_filled.png","path":"D:\\Github\\Japalura\\entry\\build\\default\\intermediates\\res\\default\\resources\\base\\media\\ic_four2three_filled.png","type":"file","isSymbolicLink":false,"fileMetaData":{"size":2073,"lastModifiedTime":1698032792000}},{"hashValue":"7b9300e26ee9c91ce3d5bfea1d3456a1","name":"ic_four2three.png","path":"D:\\Github\\Japalura\\entry\\build\\default\\intermediates\\res\\default\\resources\\base\\media\\ic_four2three.png","type":"file","isSymbolicLink":false,"fileMetaData":{"size":1764,"lastModifiedTime":1698032792000}},{"hashValue":"0dfdf79443d0a828f9dde70c302b3788","name":"ic_low.jpg","path":"D:\\Github\\Japalura\\entry\\build\\default\\intermediates\\res\\default\\resources\\base\\media\\ic_low.jpg","type":"file","isSymbolicLink":false,"fileMetaData":{"size":1720314,"lastModifiedTime":1698032792000}},{"hashValue":"77a72ec989083c315fd01a2c1db20215","name":"ic_one2one_filled.png","path":"D:\\Github\\Japalura\\entry\\build\\default\\intermediates\\res\\default\\resources\\base\\media\\ic_one2one_filled.png","type":"file","isSymbolicLink":false,"fileMetaData":{"size":1318,"lastModifiedTime":1698032792000}},{"hashValue":"41f86e36de645306aef3dca6f2709798","name":"ic_one2one.png","path":"D:\\Github\\Japalura\\entry\\build\\default\\intermediates\\res\\default\\resources\\base\\media\\ic_one2one.png","type":"file","isSymbolicLink":false,"fileMetaData":{"size":1190,"lastModifiedTime":1698032792000}},{"hashValue":"09101b4f320abae10b6b02d92ea7138b","name":"ic_original_filled.png","path":"D:\\Github\\Japalura\\entry\\build\\default\\intermediates\\res\\default\\resources\\base\\media\\ic_original_filled.png","type":"file","isSymbolicLink":false,"fileMetaData":{"size":875,"lastModifiedTime":1698032792000}},{"hashValue":"dfa3c79f3e9e90d3d70f3a04797ad81e","name":"ic_original.png","path":"D:\\Github\\Japalura\\entry\\build\\default\\intermediates\\res\\default\\resources\\base\\media\\ic_original.png","type":"file","isSymbolicLink":false,"fileMetaData":{"size":906,"lastModifiedTime":1698032792000}},{"hashValue":"6350546ea13cb77c8ce42ed1a73a57f4","name":"ic_reset.png","path":"D:\\Github\\Japalura\\entry\\build\\default\\intermediates\\res\\default\\resources\\base\\media\\ic_reset.png","type":"file","isSymbolicLink":false,"fileMetaData":{"size":2975,"lastModifiedTime":1698032792000}},{"hashValue":"4e56ee16ca6306cb4897c1019a8f8cac","name":"ic_rotate_filled.png","path":"D:\\Github\\Japalura\\entry\\build\\default\\intermediates\\res\\default\\resources\\base\\media\\ic_rotate_filled.png","type":"file","isSymbolicLink":false,"fileMetaData":{"size":2981,"lastModifiedTime":1698032792000}},{"hashValue":"d6785fa4621e2b162e8eb064d5df0cc0","name":"ic_rotate.png","path":"D:\\Github\\Japalura\\entry\\build\\default\\intermediates\\res\\default\\resources\\base\\media\\ic_rotate.png","type":"file","isSymbolicLink":false,"fileMetaData":{"size":2288,"lastModifiedTime":1698032792000}},{"hashValue":"685e937c8c01997fcfa564a91d0148c8","name":"ic_saturation_filled.png","path":"D:\\Github\\Japalura\\entry\\build\\default\\intermediates\\res\\default\\resources\\base\\media\\ic_saturation_filled.png","type":"file","isSymbolicLink":false,"fileMetaData":{"size":3810,"lastModifiedTime":1698032792000}},{"hashValue":"fd0d132daf72b0dd060359fff99c9a3b","name":"ic_saturation.png","path":"D:\\Github\\Japalura\\entry\\build\\default\\intermediates\\res\\default\\resources\\base\\media\\ic_saturation.png","type":"file","isSymbolicLink":false,"fileMetaData":{"size":3733,"lastModifiedTime":1698032792000}},{"hashValue":"682afb4da6c5329e902464493f8f6ded","name":"ic_save.png","path":"D:\\Github\\Japalura\\entry\\build\\default\\intermediates\\res\\default\\resources\\base\\media\\ic_save.png","type":"file","isSymbolicLink":false,"fileMetaData":{"size":2003,"lastModifiedTime":1698032792000}},{"hashValue":"25b07d602ae75ee387323bd996217d70","name":"ic_sixteen2nine_filled.png","path":"D:\\Github\\Japalura\\entry\\build\\default\\intermediates\\res\\default\\resources\\base\\media\\ic_sixteen2nine_filled.png","type":"file","isSymbolicLink":false,"fileMetaData":{"size":2159,"lastModifiedTime":1698032792000}},{"hashValue":"b30f2e0deb13caa1711bc5294dfb6fd6","name":"ic_sixteen2nine.png","path":"D:\\Github\\Japalura\\entry\\build\\default\\intermediates\\res\\default\\resources\\base\\media\\ic_sixteen2nine.png","type":"file","isSymbolicLink":false,"fileMetaData":{"size":1787,"lastModifiedTime":1698032792000}},{"hashValue":"3a85a13c968828bbb0080a56132dcda4","name":"ic_transparency_filled.png","path":"D:\\Github\\Japalura\\entry\\build\\default\\intermediates\\res\\default\\resources\\base\\media\\ic_transparency_filled.png","type":"file","isSymbolicLink":false,"fileMetaData":{"size":3440,"lastModifiedTime":1698032792000}},{"hashValue":"1c635c13f34c84ad644dd07a81a3c90b","name":"ic_transparency.png","path":"D:\\Github\\Japalura\\entry\\build\\default\\intermediates\\res\\default\\resources\\base\\media\\ic_transparency.png","type":"file","isSymbolicLink":false,"fileMetaData":{"size":2638,"lastModifiedTime":1698032792000}},{"hashValue":"e0ca921d52e101d5d9a64795071c9840","name":"icon.png","path":"D:\\Github\\Japalura\\entry\\build\\default\\intermediates\\res\\default\\resources\\base\\media\\icon.png","type":"file","isSymbolicLink":false,"fileMetaData":{"size":6790,"lastModifiedTime":1698032792000}}]},{"hashValue":"dfa0b78ac08b964d4fccce2bcc077ab5","name":"profile","path":"D:\\Github\\Japalura\\entry\\build\\default\\intermediates\\res\\default\\resources\\base\\profile","type":"directory","isSymbolicLink":false,"children":[{"hashValue":"4bbf78799f8a2dbf7bfbec0331266386","name":"main_pages.json","path":"D:\\Github\\Japalura\\entry\\build\\default\\intermediates\\res\\default\\resources\\base\\profile\\main_pages.json","type":"file","isSymbolicLink":false,"fileMetaData":{"size":43,"lastModifiedTime":1698032792000}}]}]},{"hashValue":"ee65c96a71abd477c92e8373f19d61f3","name":"rawfile","path":"D:\\Github\\Japalura\\entry\\build\\default\\intermediates\\res\\default\\resources\\rawfile","type":"directory","isSymbolicLink":false,"children":[{"hashValue":"c712f35b6643285bb54dcc23064a4aa5","name":"low.jpg","path":"D:\\Github\\Japalura\\entry\\build\\default\\intermediates\\res\\default\\resources\\rawfile\\low.jpg","type":"file","isSymbolicLink":false,"fileMetaData":{"size":1720314,"lastModifiedTime":1698032792000}}]}]},{"hashValue":"ec8ca4bf6f376fe713570e4224593025","name":"resources.index","path":"D:\\Github\\Japalura\\entry\\build\\default\\intermediates\\res\\default\\resources.index","type":"file","isSymbolicLink":false,"fileMetaData":{"size":4995,"lastModifiedTime":1701744980022}},{"hashValue":"cf548c199f45f6aa69e879faf588e5b5","name":"ResourceTable.txt","path":"D:\\Github\\Japalura\\entry\\build\\default\\intermediates\\res\\default\\ResourceTable.txt","type":"file","isSymbolicLink":false,"fileMetaData":{"size":2065,"lastModifiedTime":1701744980017}}]},"D:\\Github\\Japalura\\entry\\build\\default\\generated\\r\\default\\ResourceTable.h":{"hashValue":"b85d73bf8ae0dd3f0658a06a874ec9e3","name":"ResourceTable.h","path":"D:\\Github\\Japalura\\entry\\build\\default\\generated\\r\\default\\ResourceTable.h","type":"file","isSymbolicLink":false,"fileMetaData":{"size":3876,"lastModifiedTime":1701744980017}},"D:\\Github\\Japalura\\entry\\build\\default\\generated\\r\\default":{"hashValue":"6e9567c2787ea1295b8ad21301d048b8","name":"default","path":"D:\\Github\\Japalura\\entry\\build\\default\\generated\\r\\default","type":"directory","isSymbolicLink":false,"children":[{"hashValue":"b85d73bf8ae0dd3f0658a06a874ec9e3","name":"ResourceTable.h","path":"D:\\Github\\Japalura\\entry\\build\\default\\generated\\r\\default\\ResourceTable.h","type":"file","isSymbolicLink":false,"fileMetaData":{"size":3876,"lastModifiedTime":1701744980017}}]},"D:\\Github\\Japalura\\entry\\build\\default\\intermediates\\loader\\default":{"hashValue":"407d8a6f89abb8155496689712d80b09","name":"default","path":"D:\\Github\\Japalura\\entry\\build\\default\\intermediates\\loader\\default","type":"directory","isSymbolicLink":false,"children":[{"hashValue":"d764508f7fbf174db6fc1191cf1d058d","name":"loader.json","path":"D:\\Github\\Japalura\\entry\\build\\default\\intermediates\\loader\\default\\loader.json","type":"file","isSymbolicLink":false,"fileMetaData":{"size":478,"lastModifiedTime":1701744444949}}]},"D:\\Github\\Japalura\\entry\\build\\default\\intermediates\\res\\default\\ResourceTable.txt":{"hashValue":"cf548c199f45f6aa69e879faf588e5b5","name":"ResourceTable.txt","path":"D:\\Github\\Japalura\\entry\\build\\default\\intermediates\\res\\default\\ResourceTable.txt","type":"file","isSymbolicLink":false,"fileMetaData":{"size":2065,"lastModifiedTime":1701744980017}},"D:\\Github\\Japalura\\entry\\build\\default\\intermediates\\res\\default\\module.json":{"hashValue":"607a436c09420a260bf12fba1ea83946","name":"module.json","path":"D:\\Github\\Japalura\\entry\\build\\default\\intermediates\\res\\default\\module.json","type":"file","isSymbolicLink":false,"fileMetaData":{"size":3458,"lastModifiedTime":1701744980021}},"D:\\Github\\Japalura\\entry\\build\\default\\intermediates\\res\\default\\resources\\base\\profile":{"hashValue":"dfa0b78ac08b964d4fccce2bcc077ab5","name":"profile","path":"D:\\Github\\Japalura\\entry\\build\\default\\intermediates\\res\\default\\resources\\base\\profile","type":"directory","isSymbolicLink":false,"children":[{"hashValue":"4bbf78799f8a2dbf7bfbec0331266386","name":"main_pages.json","path":"D:\\Github\\Japalura\\entry\\build\\default\\intermediates\\res\\default\\resources\\base\\profile\\main_pages.json","type":"file","isSymbolicLink":false,"fileMetaData":{"size":43,"lastModifiedTime":1698032792000}}]},"D:\\Github\\Japalura\\entry\\src\\main\\ets":{"hashValue":"f4b61e6d4d9dd1ce32592eec08463dfd","name":"ets","path":"D:\\Github\\Japalura\\entry\\src\\main\\ets","type":"directory","isSymbolicLink":false,"children":[{"hashValue":"df63da9851e11e98cb4d9d2293d3f7d9","name":"common","path":"D:\\Github\\Japalura\\entry\\src\\main\\ets\\common","type":"directory","isSymbolicLink":false,"children":[{"hashValue":"0ec1b6b57e33e682894a62280380ceb5","name":"constant","path":"D:\\Github\\Japalura\\entry\\src\\main\\ets\\common\\constant","type":"directory","isSymbolicLink":false,"children":[{"hashValue":"96216628daded74622d71f5c27916d2f","name":"CommonConstants.ets","path":"D:\\Github\\Japalura\\entry\\src\\main\\ets\\common\\constant\\CommonConstants.ets","type":"file","isSymbolicLink":false,"fileMetaData":{"size":3227,"lastModifiedTime":1701742654891}}]}]},{"hashValue":"55b40975587834e3b75d1285600a6367","name":"entryability","path":"D:\\Github\\Japalura\\entry\\src\\main\\ets\\entryability","type":"directory","isSymbolicLink":false,"children":[{"hashValue":"9288e7e3c382484bd3f042be621841af","name":"EntryAbility.ets","path":"D:\\Github\\Japalura\\entry\\src\\main\\ets\\entryability\\EntryAbility.ets","type":"file","isSymbolicLink":false,"fileMetaData":{"size":2386,"lastModifiedTime":1701743500588}}]},{"hashValue":"17a10502ff9f5e7d1628e17da1122835","name":"pages","path":"D:\\Github\\Japalura\\entry\\src\\main\\ets\\pages","type":"directory","isSymbolicLink":false,"children":[{"hashValue":"b41525dc06e58c377d7e58f57ae1fa90","name":"HomePage.ets","path":"D:\\Github\\Japalura\\entry\\src\\main\\ets\\pages\\HomePage.ets","type":"file","isSymbolicLink":false,"fileMetaData":{"size":9509,"lastModifiedTime":1701744430471}}]},{"hashValue":"0dc11d25c19498810c1200b671398aeb","name":"utils","path":"D:\\Github\\Japalura\\entry\\src\\main\\ets\\utils","type":"directory","isSymbolicLink":false,"children":[{"hashValue":"132847e123bdf4a702fea92d34363cb2","name":"AdjustUtil.ets","path":"D:\\Github\\Japalura\\entry\\src\\main\\ets\\utils\\AdjustUtil.ets","type":"file","isSymbolicLink":false,"fileMetaData":{"size":6238,"lastModifiedTime":1701743594066}},{"hashValue":"13557181fabb0dba916329ddfa8014a2","name":"CropUtil.ets","path":"D:\\Github\\Japalura\\entry\\src\\main\\ets\\utils\\CropUtil.ets","type":"file","isSymbolicLink":false,"fileMetaData":{"size":3476,"lastModifiedTime":1701743613285}},{"hashValue":"f699ee6889c81fda4f94ae566209c09d","name":"DecodeUtil.ets","path":"D:\\Github\\Japalura\\entry\\src\\main\\ets\\utils\\DecodeUtil.ets","type":"file","isSymbolicLink":false,"fileMetaData":{"size":1205,"lastModifiedTime":1701743647551}},{"hashValue":"ba7f747e3531f52845634ea968b2f232","name":"EncodeUtil.ets","path":"D:\\Github\\Japalura\\entry\\src\\main\\ets\\utils\\EncodeUtil.ets","type":"file","isSymbolicLink":false,"fileMetaData":{"size":1567,"lastModifiedTime":1701743658810}},{"hashValue":"74e536e5311ffe31e48cde3d13db39bc","name":"LoggerUtil.ets","path":"D:\\Github\\Japalura\\entry\\src\\main\\ets\\utils\\LoggerUtil.ets","type":"file","isSymbolicLink":false,"fileMetaData":{"size":979,"lastModifiedTime":1701743682227}},{"hashValue":"6f4e77fdcedf236ceb771c421615aa43","name":"OpacityUtil.ets","path":"D:\\Github\\Japalura\\entry\\src\\main\\ets\\utils\\OpacityUtil.ets","type":"file","isSymbolicLink":false,"fileMetaData":{"size":599,"lastModifiedTime":1701743728371}}]},{"hashValue":"f3809fcc1e521e5e790591bc25ffcd63","name":"view","path":"D:\\Github\\Japalura\\entry\\src\\main\\ets\\view","type":"directory","isSymbolicLink":false,"children":[{"hashValue":"42840b1492c8e50da3e88d7620cddfc8","name":"AdjustContentView.ets","path":"D:\\Github\\Japalura\\entry\\src\\main\\ets\\view\\AdjustContentView.ets","type":"file","isSymbolicLink":false,"fileMetaData":{"size":6759,"lastModifiedTime":1701743763554}}]},{"hashValue":"58deadecb900ca9d96517238d2ac1dc4","name":"viewmodel","path":"D:\\Github\\Japalura\\entry\\src\\main\\ets\\viewmodel","type":"directory","isSymbolicLink":false,"children":[{"hashValue":"7993e2da84ddeb718b3b9a0b830a2d58","name":"IconListViewModel.ets","path":"D:\\Github\\Japalura\\entry\\src\\main\\ets\\viewmodel\\IconListViewModel.ets","type":"file","isSymbolicLink":false,"fileMetaData":{"size":1336,"lastModifiedTime":1701743851145}},{"hashValue":"9c8a2153263e9af8e0ac69f9e6049479","name":"MessageItem.ets","path":"D:\\Github\\Japalura\\entry\\src\\main\\ets\\viewmodel\\MessageItem.ets","type":"file","isSymbolicLink":false,"fileMetaData":{"size":415,"lastModifiedTime":1701743979837}},{"hashValue":"fa58c3989be02ab3123a4bc5a9124602","name":"OptionViewModel.ets","path":"D:\\Github\\Japalura\\entry\\src\\main\\ets\\viewmodel\\OptionViewModel.ets","type":"file","isSymbolicLink":false,"fileMetaData":{"size":759,"lastModifiedTime":1701743994300}},{"hashValue":"d36b59f111854e368491e5f6202c0d3f","name":"RegionItem.ets","path":"D:\\Github\\Japalura\\entry\\src\\main\\ets\\viewmodel\\RegionItem.ets","type":"file","isSymbolicLink":false,"fileMetaData":{"size":237,"lastModifiedTime":1701744044150}}]},{"hashValue":"e09b754c6f00981c73198705c50e9861","name":"workers","path":"D:\\Github\\Japalura\\entry\\src\\main\\ets\\workers","type":"directory","isSymbolicLink":false,"children":[{"hashValue":"4cc7148657905ee941b2482862d99910","name":"AdjustBrightnessWork.ts","path":"D:\\Github\\Japalura\\entry\\src\\main\\ets\\workers\\AdjustBrightnessWork.ts","type":"file","isSymbolicLink":false,"fileMetaData":{"size":1555,"lastModifiedTime":1701744063155}},{"hashValue":"f10af8394155398d079e635b3172b8dd","name":"AdjustSaturationWork.ts","path":"D:\\Github\\Japalura\\entry\\src\\main\\ets\\workers\\AdjustSaturationWork.ts","type":"file","isSymbolicLink":false,"fileMetaData":{"size":1558,"lastModifiedTime":1701744079445}}]}]},"D:\\Github\\Japalura\\entry\\build\\default\\intermediates\\loader_out\\default\\ets":{"hashValue":"11cbd33e8664c6565d6eecf89cdf8640","name":"ets","path":"D:\\Github\\Japalura\\entry\\build\\default\\intermediates\\loader_out\\default\\ets","type":"directory","isSymbolicLink":false,"children":[{"hashValue":"f4c270bf25a3f979b69e13b0dee0937e","name":"sourceMaps.map","path":"D:\\Github\\Japalura\\entry\\build\\default\\intermediates\\loader_out\\default\\ets\\sourceMaps.map","type":"file","isSymbolicLink":false,"fileMetaData":{"size":212736,"lastModifiedTime":1701744983811}}]},"D:\\Github\\Japalura\\entry\\build\\default\\intermediates\\res\\default\\resources":{"hashValue":"9fcd16d3a213e2b3072f3e3450e7209e","name":"resources","path":"D:\\Github\\Japalura\\entry\\build\\default\\intermediates\\res\\default\\resources","type":"directory","isSymbolicLink":false,"children":[{"hashValue":"627ae185d7c80a27bc9e6593d01b2c93","name":"base","path":"D:\\Github\\Japalura\\entry\\build\\default\\intermediates\\res\\default\\resources\\base","type":"directory","isSymbolicLink":false,"children":[{"hashValue":"541d81193ed96814b245f998cff73fee","name":"media","path":"D:\\Github\\Japalura\\entry\\build\\default\\intermediates\\res\\default\\resources\\base\\media","type":"directory","isSymbolicLink":false,"children":[{"hashValue":"24d7fb7a55a72b5304fe119a3b8daa6f","name":"app_icon.png","path":"D:\\Github\\Japalura\\entry\\build\\default\\intermediates\\res\\default\\resources\\base\\media\\app_icon.png","type":"file","isSymbolicLink":false,"fileMetaData":{"size":6790,"lastModifiedTime":1698032792000}},{"hashValue":"88086604bdd89994d4e56e2231ce70d4","name":"ic_adjust_filled.png","path":"D:\\Github\\Japalura\\entry\\build\\default\\intermediates\\res\\default\\resources\\base\\media\\ic_adjust_filled.png","type":"file","isSymbolicLink":false,"fileMetaData":{"size":2682,"lastModifiedTime":1698032792000}},{"hashValue":"2902d4d7ed783be0dcb036118340c672","name":"ic_adjust.png","path":"D:\\Github\\Japalura\\entry\\build\\default\\intermediates\\res\\default\\resources\\base\\media\\ic_adjust.png","type":"file","isSymbolicLink":false,"fileMetaData":{"size":1876,"lastModifiedTime":1698032792000}},{"hashValue":"c7459d16d3e71b34392050b605fff731","name":"ic_anti_clockwise.png","path":"D:\\Github\\Japalura\\entry\\build\\default\\intermediates\\res\\default\\resources\\base\\media\\ic_anti_clockwise.png","type":"file","isSymbolicLink":false,"fileMetaData":{"size":1788,"lastModifiedTime":1698032792000}},{"hashValue":"ae6f78e69f8c64a0d14cf65c46717acf","name":"ic_brightness_filled.png","path":"D:\\Github\\Japalura\\entry\\build\\default\\intermediates\\res\\default\\resources\\base\\media\\ic_brightness_filled.png","type":"file","isSymbolicLink":false,"fileMetaData":{"size":3875,"lastModifiedTime":1698032792000}},{"hashValue":"b2bbf1e56363f96531af260603770218","name":"ic_brightness.png","path":"D:\\Github\\Japalura\\entry\\build\\default\\intermediates\\res\\default\\resources\\base\\media\\ic_brightness.png","type":"file","isSymbolicLink":false,"fileMetaData":{"size":2607,"lastModifiedTime":1698032792000}},{"hashValue":"568780f5edf38dcecd548e828addfa34","name":"ic_clockwise.png","path":"D:\\Github\\Japalura\\entry\\build\\default\\intermediates\\res\\default\\resources\\base\\media\\ic_clockwise.png","type":"file","isSymbolicLink":false,"fileMetaData":{"size":1881,"lastModifiedTime":1698032792000}},{"hashValue":"8e5dc91eca088e0041a9ba9b85111341","name":"ic_crop_filled.png","path":"D:\\Github\\Japalura\\entry\\build\\default\\intermediates\\res\\default\\resources\\base\\media\\ic_crop_filled.png","type":"file","isSymbolicLink":false,"fileMetaData":{"size":1592,"lastModifiedTime":1698032792000}},{"hashValue":"c50eb56c591fd528aa56e3678f027629","name":"ic_crop.png","path":"D:\\Github\\Japalura\\entry\\build\\default\\intermediates\\res\\default\\resources\\base\\media\\ic_crop.png","type":"file","isSymbolicLink":false,"fileMetaData":{"size":1221,"lastModifiedTime":1698032792000}},{"hashValue":"7130d2237bdb6473016b0405d6155fb1","name":"ic_four2three_filled.png","path":"D:\\Github\\Japalura\\entry\\build\\default\\intermediates\\res\\default\\resources\\base\\media\\ic_four2three_filled.png","type":"file","isSymbolicLink":false,"fileMetaData":{"size":2073,"lastModifiedTime":1698032792000}},{"hashValue":"7b9300e26ee9c91ce3d5bfea1d3456a1","name":"ic_four2three.png","path":"D:\\Github\\Japalura\\entry\\build\\default\\intermediates\\res\\default\\resources\\base\\media\\ic_four2three.png","type":"file","isSymbolicLink":false,"fileMetaData":{"size":1764,"lastModifiedTime":1698032792000}},{"hashValue":"0dfdf79443d0a828f9dde70c302b3788","name":"ic_low.jpg","path":"D:\\Github\\Japalura\\entry\\build\\default\\intermediates\\res\\default\\resources\\base\\media\\ic_low.jpg","type":"file","isSymbolicLink":false,"fileMetaData":{"size":1720314,"lastModifiedTime":1698032792000}},{"hashValue":"77a72ec989083c315fd01a2c1db20215","name":"ic_one2one_filled.png","path":"D:\\Github\\Japalura\\entry\\build\\default\\intermediates\\res\\default\\resources\\base\\media\\ic_one2one_filled.png","type":"file","isSymbolicLink":false,"fileMetaData":{"size":1318,"lastModifiedTime":1698032792000}},{"hashValue":"41f86e36de645306aef3dca6f2709798","name":"ic_one2one.png","path":"D:\\Github\\Japalura\\entry\\build\\default\\intermediates\\res\\default\\resources\\base\\media\\ic_one2one.png","type":"file","isSymbolicLink":false,"fileMetaData":{"size":1190,"lastModifiedTime":1698032792000}},{"hashValue":"09101b4f320abae10b6b02d92ea7138b","name":"ic_original_filled.png","path":"D:\\Github\\Japalura\\entry\\build\\default\\intermediates\\res\\default\\resources\\base\\media\\ic_original_filled.png","type":"file","isSymbolicLink":false,"fileMetaData":{"size":875,"lastModifiedTime":1698032792000}},{"hashValue":"dfa3c79f3e9e90d3d70f3a04797ad81e","name":"ic_original.png","path":"D:\\Github\\Japalura\\entry\\build\\default\\intermediates\\res\\default\\resources\\base\\media\\ic_original.png","type":"file","isSymbolicLink":false,"fileMetaData":{"size":906,"lastModifiedTime":1698032792000}},{"hashValue":"6350546ea13cb77c8ce42ed1a73a57f4","name":"ic_reset.png","path":"D:\\Github\\Japalura\\entry\\build\\default\\intermediates\\res\\default\\resources\\base\\media\\ic_reset.png","type":"file","isSymbolicLink":false,"fileMetaData":{"size":2975,"lastModifiedTime":1698032792000}},{"hashValue":"4e56ee16ca6306cb4897c1019a8f8cac","name":"ic_rotate_filled.png","path":"D:\\Github\\Japalura\\entry\\build\\default\\intermediates\\res\\default\\resources\\base\\media\\ic_rotate_filled.png","type":"file","isSymbolicLink":false,"fileMetaData":{"size":2981,"lastModifiedTime":1698032792000}},{"hashValue":"d6785fa4621e2b162e8eb064d5df0cc0","name":"ic_rotate.png","path":"D:\\Github\\Japalura\\entry\\build\\default\\intermediates\\res\\default\\resources\\base\\media\\ic_rotate.png","type":"file","isSymbolicLink":false,"fileMetaData":{"size":2288,"lastModifiedTime":1698032792000}},{"hashValue":"685e937c8c01997fcfa564a91d0148c8","name":"ic_saturation_filled.png","path":"D:\\Github\\Japalura\\entry\\build\\default\\intermediates\\res\\default\\resources\\base\\media\\ic_saturation_filled.png","type":"file","isSymbolicLink":false,"fileMetaData":{"size":3810,"lastModifiedTime":1698032792000}},{"hashValue":"fd0d132daf72b0dd060359fff99c9a3b","name":"ic_saturation.png","path":"D:\\Github\\Japalura\\entry\\build\\default\\intermediates\\res\\default\\resources\\base\\media\\ic_saturation.png","type":"file","isSymbolicLink":false,"fileMetaData":{"size":3733,"lastModifiedTime":1698032792000}},{"hashValue":"682afb4da6c5329e902464493f8f6ded","name":"ic_save.png","path":"D:\\Github\\Japalura\\entry\\build\\default\\intermediates\\res\\default\\resources\\base\\media\\ic_save.png","type":"file","isSymbolicLink":false,"fileMetaData":{"size":2003,"lastModifiedTime":1698032792000}},{"hashValue":"25b07d602ae75ee387323bd996217d70","name":"ic_sixteen2nine_filled.png","path":"D:\\Github\\Japalura\\entry\\build\\default\\intermediates\\res\\default\\resources\\base\\media\\ic_sixteen2nine_filled.png","type":"file","isSymbolicLink":false,"fileMetaData":{"size":2159,"lastModifiedTime":1698032792000}},{"hashValue":"b30f2e0deb13caa1711bc5294dfb6fd6","name":"ic_sixteen2nine.png","path":"D:\\Github\\Japalura\\entry\\build\\default\\intermediates\\res\\default\\resources\\base\\media\\ic_sixteen2nine.png","type":"file","isSymbolicLink":false,"fileMetaData":{"size":1787,"lastModifiedTime":1698032792000}},{"hashValue":"3a85a13c968828bbb0080a56132dcda4","name":"ic_transparency_filled.png","path":"D:\\Github\\Japalura\\entry\\build\\default\\intermediates\\res\\default\\resources\\base\\media\\ic_transparency_filled.png","type":"file","isSymbolicLink":false,"fileMetaData":{"size":3440,"lastModifiedTime":1698032792000}},{"hashValue":"1c635c13f34c84ad644dd07a81a3c90b","name":"ic_transparency.png","path":"D:\\Github\\Japalura\\entry\\build\\default\\intermediates\\res\\default\\resources\\base\\media\\ic_transparency.png","type":"file","isSymbolicLink":false,"fileMetaData":{"size":2638,"lastModifiedTime":1698032792000}},{"hashValue":"e0ca921d52e101d5d9a64795071c9840","name":"icon.png","path":"D:\\Github\\Japalura\\entry\\build\\default\\intermediates\\res\\default\\resources\\base\\media\\icon.png","type":"file","isSymbolicLink":false,"fileMetaData":{"size":6790,"lastModifiedTime":1698032792000}}]},{"hashValue":"dfa0b78ac08b964d4fccce2bcc077ab5","name":"profile","path":"D:\\Github\\Japalura\\entry\\build\\default\\intermediates\\res\\default\\resources\\base\\profile","type":"directory","isSymbolicLink":false,"children":[{"hashValue":"4bbf78799f8a2dbf7bfbec0331266386","name":"main_pages.json","path":"D:\\Github\\Japalura\\entry\\build\\default\\intermediates\\res\\default\\resources\\base\\profile\\main_pages.json","type":"file","isSymbolicLink":false,"fileMetaData":{"size":43,"lastModifiedTime":1698032792000}}]}]},{"hashValue":"ee65c96a71abd477c92e8373f19d61f3","name":"rawfile","path":"D:\\Github\\Japalura\\entry\\build\\default\\intermediates\\res\\default\\resources\\rawfile","type":"directory","isSymbolicLink":false,"children":[{"hashValue":"c712f35b6643285bb54dcc23064a4aa5","name":"low.jpg","path":"D:\\Github\\Japalura\\entry\\build\\default\\intermediates\\res\\default\\resources\\rawfile\\low.jpg","type":"file","isSymbolicLink":false,"fileMetaData":{"size":1720314,"lastModifiedTime":1698032792000}}]}]},"D:\\Github\\Japalura\\entry\\build\\default\\intermediates\\res\\default\\resources.index":{"hashValue":"c0070a11604c57497f3fc361589fdb3c","name":"resources.index","path":"D:\\Github\\Japalura\\entry\\build\\default\\intermediates\\res\\default\\resources.index","type":"file","isSymbolicLink":false,"fileMetaData":{"size":5770,"lastModifiedTime":1701744446511}},"D:\\Github\\Japalura\\entry\\build\\default\\outputs\\default\\entry-default-unsigned.hap":{"hashValue":"fb0fda859ae49867ec963bb31a18f216","name":"entry-default-unsigned.hap","path":"D:\\Github\\Japalura\\entry\\build\\default\\outputs\\default\\entry-default-unsigned.hap","type":"file","isSymbolicLink":false,"fileMetaData":{"size":3911125,"lastModifiedTime":1701744453740}},"D:\\Github\\Japalura\\entry\\build\\default\\intermediates\\loader_out\\default\\js":{"hashValue":"","name":"emptyroot","path":"","type":"unknown","isSymbolicLink":false,"children":[]}}